fspi_analysis/__init__.py
fspi_analysis/fspi_gui.py
fspi_analysis/napari.yaml
fspi_analysis/_tests/__init__.py
fspi_analysis-0.1.2.dist-info/licenses/LICENSE
fspi_analysis-0.1.2.dist-info/METADATA
fspi_analysis-0.1.2.dist-info/WHEEL
fspi_analysis-0.1.2.dist-info/entry_points.txt
fspi_analysis-0.1.2.dist-info/top_level.txt
fspi_analysis-0.1.2.dist-info/RECORD
