Metadata-Version: 2.4
Name: fspi_analysis
Version: 0.1.2
Summary: A simple plugin to perform fspi analysis within napari
Author: Olivier Cahn
Author-email: oc124@ic.ac.uk
License: 
Project-URL: Bug Tracker, https://github.com/engpol/fspi_analysis/issues
Project-URL: Documentation, https://github.com/engpol/fspi_analysis#README.md
Project-URL: Source Code, https://github.com/engpol/fspi_analysis
Project-URL: User Support, https://github.com/engpol/fspi_analysis/issues
Classifier: Development Status :: 2 - Pre-Alpha
Classifier: Framework :: napari
Classifier: Intended Audience :: Developers
Classifier: License :: OSI Approved :: GNU General Public License v3 (GPLv3)
Classifier: Operating System :: OS Independent
Classifier: Programming Language :: Python
Classifier: Programming Language :: Python :: 3
Classifier: Programming Language :: Python :: 3 :: Only
Classifier: Programming Language :: Python :: 3.10
Classifier: Programming Language :: Python :: 3.11
Classifier: Programming Language :: Python :: 3.12
Classifier: Programming Language :: Python :: 3.13
Classifier: Topic :: Scientific/Engineering :: Image Processing
Requires-Python: >=3.10
License-File: LICENSE
Requires-Dist: numpy
Requires-Dist: magicgui
Requires-Dist: qtpy
Requires-Dist: scikit-image
Requires-Dist: pandas
Requires-Dist: napari
Provides-Extra: testing
Requires-Dist: tox; extra == "testing"
Requires-Dist: pytest; extra == "testing"
Requires-Dist: pytest-cov; extra == "testing"
Dynamic: license-file
